pyasync/__init__.py
pyasync/runtime.py
python_async-0.3.0.dist-info/METADATA
python_async-0.3.0.dist-info/WHEEL
python_async-0.3.0.dist-info/top_level.txt
python_async-0.3.0.dist-info/RECORD
