Metadata-Version: 2.4
Name: python-async
Version: 0.3.0
Summary: Thread and Process-based parallelism for Python. Simple, explicit API for running tasks in parallel.
Author-email: "Marcio Bernardes B. Jr." <marciobernardes39@gmail.com>
License: MIT
Project-URL: Homepage, https://github.com/marciobbj/pyasync
Project-URL: Repository, https://github.com/marciobbj/pyasync
Project-URL: Issues, https://github.com/marciobbj/pyasync/issues
Keywords: parallel,threading,concurrency,threadpool,multithread
Classifier: Development Status :: 3 - Alpha
Classifier: Intended Audience :: Developers
Classifier: License :: OSI Approved :: MIT License
Classifier: Operating System :: OS Independent
Classifier: Programming Language :: Python :: 3
Classifier: Programming Language :: Python :: 3.10
Classifier: Programming Language :: Python :: 3.11
Classifier: Programming Language :: Python :: 3.12
Classifier: Topic :: Software Development :: Libraries :: Python Modules
Requires-Python: >=3.10
